<!-- min-version: 24 -->
<!-- snippet: om:model -->
  <model>
    <ModelOptions>
      <option name="MAX_DENS_CORRECTION" value="true"/>
      <option name="INNATE_MAX_DENS" value="false"/>
      <option name="INDIRECT_MORTALITY_FIX" value="false"/>
    </ModelOptions>
    <clinical healthSystemMemory="6"/>
    <human>
      <availabilityToMosquitoes>
        <group lowerbound="0.0" value="0.225940909648"/>
        <group lowerbound="1.0" value="0.286173633441"/>
        <group lowerbound="2.0" value="0.336898395722"/>
        <group lowerbound="3.0" value="0.370989854675"/>
        <group lowerbound="4.0" value="0.403114915112"/>
        <group lowerbound="5.0" value="0.442585112522"/>
        <group lowerbound="6.0" value="0.473839351511"/>
        <group lowerbound="7.0" value="0.512630464378"/>
        <group lowerbound="8.0" value="0.54487872702"/>
        <group lowerbound="9.0" value="0.581527755812"/>
        <group lowerbound="10.0" value="0.630257580698"/>
        <group lowerbound="11.0" value="0.663063362714"/>
        <group lowerbound="12.0" value="0.702417432755"/>
        <group lowerbound="13.0" value="0.734605377277"/>
        <group lowerbound="14.0" value="0.788908765653"/>
        <group lowerbound="15.0" value="0.839587932303"/>
        <group lowerbound="20.0" value="1.0"/>
        <group lowerbound="20.0" value="1.0"/>
        <!-- repeated parameter *IS* required, otherwise interpolation will
        make parameter continually increase and the "adult age" will be wrong. -->
      </availabilityToMosquitoes>
    </human>
    <parameters interval="5" iseed="0" latentp="3">
      <!-- run id=121 modelVers=64 parameterization id=253695 sampling date=2009-12-01 01:58:05 lossfunction=49.46573 -->
      <parameter include="0" name="'-ln(1-Sinf)'" number="1" value="0.050736"/>
      <parameter include="0" name="Estar" number="2" value="0.03247"/>
      <parameter include="1" name="Simm" number="3" value="0.148481"/>
      <parameter include="1" name="Xstar_p" number="4" value="2920.741499"/>
      <parameter include="1" name="gamma_p" number="5" value="2.105994"/>
      <parameter include="1" name="sigma2i" number="6" value="10.26069"/>
      <parameter include="1" name="CumulativeYstar" number="7" value="68564384.7102"/>
      <parameter include="1" name="CumulativeHstar" number="8" value="71.676733"/>
      <parameter include="1" name="'-ln(1-alpha_m)'" number="9" value="2.411434"/>
      <parameter include="1" name="decay_m" number="10" value="2.717773"/>
      <parameter include="1" name="sigma2_0" number="11" value="0.675205"/>
      <parameter include="1" name="Xstar_v" number="12" value="0.918329"/>
      <parameter include="1" name="Ystar2" number="13" value="10239.500357"/>
      <parameter include="1" name="alpha" number="14" value="138185.950622"/>
      <parameter include="1" name="Density bias (non Garki)" number="15" value="0.150426"/>
      <parameter include="0" name="No Use 1" number="16" value="1.0"/>
      <parameter include="1" name="log oddsr CF community" number="17" value="0.739609"/>
      <parameter include="1" name="Indirect risk cofactor" number="18" value="0.020977"/>
      <parameter include="1" name="Non-malaria infant mortality" number="19" value="45.100508"/>
      <parameter include="1" name="Density bias (Garki)" number="20" value="4.962416"/>
      <parameter include="1" name="Severe Malaria Threshhold" number="21" value="329389.646588"/>
      <parameter include="0" name="Immunity Penalty" number="22" value="1.0"/>
      <parameter include="0" name="Immune effector decay" number="23" value="9e-06"/>
      <parameter include="1" name="comorbidity intercept" number="24" value="0.076526"/>
      <parameter include="1" name="Ystar half life" number="25" value="0.265169"/>
      <parameter include="1" name="Ystar1" number="26" value="0.618741"/>
      <parameter include="0" name="Asex immune decay" number="27" value="0.0"/>
      <parameter include="1" name="Ystar0" number="28" value="576.377794"/>
      <parameter include="1" name="Idete multiplier" number="29" value="2.697203"/>
      <parameter include="1" name="critical age for comorbidity" number="30" value="0.124479"/>
    </parameters>
  </model>
